cssjson/__init__.py
cssjson-1.0.0.dist-info/LICENSE
cssjson-1.0.0.dist-info/METADATA
cssjson-1.0.0.dist-info/WHEEL
cssjson-1.0.0.dist-info/dependency_links.txt
cssjson-1.0.0.dist-info/top_level.txt
cssjson-1.0.0.dist-info/RECORD
