Metadata-Version: 2.1
Name: cssjson
Version: 1.0.0
Summary: Converts CSS to JSON format
Home-page: https://github.com/CITGuru/cssjson/
Author: Oyetoke Toby
Author-email: oyetoketoby80@gmail.com
License: MIT
Download-URL: https://github.com/CITGuru/cssjson/archive/1.0.0.tar.gz
Platform: UNKNOWN
Classifier: Development Status :: 1 - Planning
Classifier: Natural Language :: English
Classifier: Programming Language :: Python :: 2.7
Classifier: Programming Language :: Python :: 3.6
Classifier: Environment :: Console
Classifier: Intended Audience :: Developers
Classifier: License :: OSI Approved :: MIT License
Classifier: Operating System :: OS Independent
Classifier: Topic :: Software Development :: User Interfaces
Classifier: Topic :: Software Development :: Libraries :: Application Frameworks
Requires-Dist: cssutils
